.VERSION
AUTHORS.rst
CONTRIBUTING.rst
HISTORY.rst
LICENSE
MANIFEST.in
Pipfile
Pipfile.lock
README.rst
USAGE.rst
dev-requirements.txt
requirements.txt
setup.cfg
setup.py
_CI/__init__.py
_CI/configuration/__init__.py
_CI/configuration/configuration.py
_CI/library/__init__.py
_CI/library/library.py
_CI/scripts/__init__.py
_CI/scripts/bootstrap.py
_CI/scripts/build.py
_CI/scripts/document.py
_CI/scripts/graph.py
_CI/scripts/lint.py
_CI/scripts/tag.py
_CI/scripts/test.py
_CI/scripts/upload.py
docs/Makefile
docs/authors.rst
docs/conf.py
docs/contributing.rst
docs/history.rst
docs/index.rst
docs/installation.rst
docs/modules.rst
docs/pystrava.rst
docs/readme.rst
docs/usage.rst
pystrava/.VERSION
pystrava/__init__.py
pystrava/_version.py
pystrava/constants.py
pystrava/pystrava.py
pystrava/pystravaexceptions.py
pystrava/test_refresh.py
pystrava.egg-info/PKG-INFO
pystrava.egg-info/SOURCES.txt
pystrava.egg-info/dependency_links.txt
pystrava.egg-info/not-zip-safe
pystrava.egg-info/requires.txt
pystrava.egg-info/top_level.txt