Metadata-Version: 1.1
Name: pystrava
Version: 0.2.2
Summary: Transparent authentication for Strava API
Home-page: https://github.com/wefner/pystrava
Author: Oriol Fabregas
Author-email: fabregas.oriol@gmail.com
License: MIT
Keywords: pystrava strava auth
Platform: UNKNOWN
Classifier: Development Status :: 3 - Alpha
Classifier: Intended Audience :: Developers
Classifier: License :: OSI Approved :: MIT License
Classifier: Natural Language :: English
Classifier: Programming Language :: Python :: 3 :: Only
